selib/__init__.py
selib/selib.py
se_lib-0.199.dist-info/METADATA
se_lib-0.199.dist-info/WHEEL
se_lib-0.199.dist-info/licenses/LICENSE
se_lib-0.199.dist-info/RECORD
