Metadata-Version: 2.1
Name: se-lib
Version: 0.199
Summary: Systems Engineering Library (SElib)
Project-URL: Homepage, http://pyml.fun
Author-email: se-lib Development Team <info@se-lib.org>
License-File: LICENSE
Classifier: License :: OSI Approved :: MIT License
Classifier: Operating System :: OS Independent
Classifier: Programming Language :: Python :: 3
Requires-Python: >=3.7
